flask_sshtunnel.py
Flask_sshtunnel-0.1b2.dist-info/LICENSE
Flask_sshtunnel-0.1b2.dist-info/METADATA
Flask_sshtunnel-0.1b2.dist-info/WHEEL
Flask_sshtunnel-0.1b2.dist-info/top_level.txt
Flask_sshtunnel-0.1b2.dist-info/RECORD
