Metadata-Version: 1.1
Name: Flask-sshtunnel
Version: 0.1b2
Summary: sshtunnel extension for flask
Home-page: https://github.com/heyoni/flask-tunnel
Author: Jonathan Revah
Author-email: jrevah@gmail.com
License: MIT
Platform: any
Classifier: Environment :: Web Environment
Classifier: Intended Audience :: Developers
Classifier: License :: OSI Approved :: MIT License
Classifier: Operating System :: OS Independent
Classifier: Programming Language :: Python
Classifier: Framework :: Flask
Classifier: Topic :: Internet :: WWW/HTTP :: Dynamic Content
Classifier: Topic :: Software Development :: Libraries :: Python Modules
